reflex_github_button/__init__.py
reflex_github_button/github_button.py
reflex_github_button-0.1.7.dist-info/METADATA
reflex_github_button-0.1.7.dist-info/WHEEL
reflex_github_button-0.1.7.dist-info/top_level.txt
reflex_github_button-0.1.7.dist-info/RECORD
